pyvisigraph/__init__.py
pyvisigraph/graph.py
pyvisigraph/shape_work.py
pyvisigraph/visi_graph.py
pyvisigraph/visible_vertices.py
pyvisigraph-2.0.5.dist-info/LICENSE.txt
pyvisigraph-2.0.5.dist-info/METADATA
pyvisigraph-2.0.5.dist-info/WHEEL
pyvisigraph-2.0.5.dist-info/top_level.txt
pyvisigraph-2.0.5.dist-info/RECORD
