Metadata-Version: 2.1
Name: pyvisigraph
Version: 2.0.5
Summary: Given a set of simple obstacle polygons, build a visibility graph and find the shortest path between two points.
Home-page: https://github.com/pingou2712/pyvisigraph
Download-URL: https://github.com/pingou2712/pyvisigraph/tarball/2.0.5
Author: Vincent Laffargue
Author-email: vincent.laffargue@gmail.com
Keywords: visibility,graph,shortest
License-File: LICENSE.txt
Requires-Dist: geopandas (>=0.14.3)
Requires-Dist: geopy (>=2.4.1)
Requires-Dist: matplotlib (>=3.8.4)
Requires-Dist: networkx (>=3.3)
Requires-Dist: tqdm (>=4.23.4)
